cirrocumulus/__init__.py
cirrocumulus/__main__.py
cirrocumulus/abstract_backed_dataset.py
cirrocumulus/abstract_dataset.py
cirrocumulus/abstract_db.py
cirrocumulus/anndata_dataset.py
cirrocumulus/anndata_util.py
cirrocumulus/anndata_zarr.py
cirrocumulus/api.py
cirrocumulus/auth_exception.py
cirrocumulus/blueprint_util.py
cirrocumulus/cloud_firestore.py
cirrocumulus/concat.py
cirrocumulus/data_processing.py
cirrocumulus/dataset_api.py
cirrocumulus/diff_exp.py
cirrocumulus/dotplot_aggregator.py
cirrocumulus/embedding_aggregator.py
cirrocumulus/envir.py
cirrocumulus/fdr.py
cirrocumulus/feature_aggregator.py
cirrocumulus/google_auth.py
cirrocumulus/groupby.py
cirrocumulus/h5ad_dataset.py
cirrocumulus/h5ad_output.py
cirrocumulus/ids_aggregator.py
cirrocumulus/invalid_usage.py
cirrocumulus/io_util.py
cirrocumulus/job_api.py
cirrocumulus/json_io.py
cirrocumulus/jsonl_io.py
cirrocumulus/launch.py
cirrocumulus/local_db_api.py
cirrocumulus/mongo_db.py
cirrocumulus/no_auth.py
cirrocumulus/okta_auth.py
cirrocumulus/parquet_dataset.py
cirrocumulus/parquet_output.py
cirrocumulus/prepare_data.py
cirrocumulus/serve.py
cirrocumulus/seurat2h5ad.R
cirrocumulus/stat_util.py
cirrocumulus/tiledb_dataset.py
cirrocumulus/unique_aggregator.py
cirrocumulus/util.py
cirrocumulus/zarr_dataset.py
cirrocumulus/zarr_output.py
cirrocumulus/client/asset-manifest.json
cirrocumulus/client/favicon.ico
cirrocumulus/client/index.html
cirrocumulus/client/manifest.json
cirrocumulus/client/privacy_policy.html
cirrocumulus/client/static/js/main.f3957c8b.js
cirrocumulus/client/static/js/main.f3957c8b.js.LICENSE.txt
cirrocumulus/client/static/js/main.f3957c8b.js.map
cirrocumulus/ot/__init__.py
cirrocumulus/ot/population.py
cirrocumulus/ot/transport_map_model.py
cirrocumulus/ot/util.py
cirrocumulus-1.1.61.dist-info/METADATA
cirrocumulus-1.1.61.dist-info/WHEEL
cirrocumulus-1.1.61.dist-info/entry_points.txt
cirrocumulus-1.1.61.dist-info/licenses/LICENSE
cirrocumulus-1.1.61.dist-info/RECORD
