Metadata-Version: 2.4
Name: cirrocumulus
Version: 1.1.61
Summary: Bring your single-cell data to life
Project-URL: Source, https://github.com/lilab-bcb/cirrocumulus
Project-URL: Documentation, https://cirrocumulus.readthedocs.io/
Author-email: Joshua Gould <cirrocumulus@googlegroups.com>
License: BSD 3-Clause License
License-File: LICENSE
Classifier: Development Status :: 5 - Production/Stable
Classifier: Intended Audience :: Developers
Classifier: Intended Audience :: Science/Research
Classifier: License :: OSI Approved :: BSD License
Classifier: Natural Language :: English
Classifier: Operating System :: OS Independent
Classifier: Programming Language :: Python :: 3
Classifier: Programming Language :: Python :: Implementation :: PyPy
Classifier: Topic :: Scientific/Engineering :: Bio-Informatics
Classifier: Topic :: Scientific/Engineering :: Visualization
Requires-Python: >=3.11
Requires-Dist: anndata
Requires-Dist: cachecontrol
Requires-Dist: flask
Requires-Dist: flask-compress
Requires-Dist: fsspec
Requires-Dist: gunicorn
Requires-Dist: numpy
Requires-Dist: pandas
Requires-Dist: pymongo
Requires-Dist: requests
Requires-Dist: scipy
Requires-Dist: zarr<3
Provides-Extra: parquet
Requires-Dist: pyarrow; extra == 'parquet'
Provides-Extra: test
Requires-Dist: mongomock; extra == 'test'
Requires-Dist: pytest; extra == 'test'
Requires-Dist: scanpy; extra == 'test'
